ld_openfeature/__init__.py
ld_openfeature/impl/context_converter.py
ld_openfeature/impl/details_converter.py
ld_openfeature/provider.py
ld_openfeature/py.typed
launchdarkly_openfeature_server-0.5.1.dist-info/METADATA
launchdarkly_openfeature_server-0.5.1.dist-info/WHEEL
launchdarkly_openfeature_server-0.5.1.dist-info/licenses/LICENSE
launchdarkly_openfeature_server-0.5.1.dist-info/RECORD
