Metadata-Version: 2.4
Name: launchdarkly-openfeature-server
Version: 0.5.1
Summary: An OpenFeature provider for the LaunchDarkly Python server SDK
License: Apache-2.0
License-File: LICENSE
Author: LaunchDarkly
Author-email: dev@launchdarkly.com
Requires-Python: >=3.9,<4.0
Classifier: Intended Audience :: Developers
Classifier: License :: OSI Approved :: Apache Software License
Classifier: Operating System :: OS Independent
Classifier: Programming Language :: Python :: 3
Classifier: Programming Language :: Python :: 3.9
Classifier: Programming Language :: Python :: 3.10
Classifier: Programming Language :: Python :: 3.11
Classifier: Programming Language :: Python :: 3.12
Classifier: Programming Language :: Python :: 3.13
Classifier: Programming Language :: Python :: 3.14
Classifier: Topic :: Software Development
Classifier: Topic :: Software Development :: Libraries
Requires-Dist: launchdarkly-server-sdk (<10)
Requires-Dist: openfeature-sdk (>=0.8.0,<1)
Project-URL: Documentation, https://launchdarkly-openfeature-python-sdk.readthedocs.io/en/latest/
Project-URL: Repository, https://github.com/launchdarkly/openfeature-python-server
